idioma/__init__.py
idioma/async_gtoken.py
idioma/async_translator.py
idioma/base_gtoken.py
idioma/base_translator.py
idioma/constants.py
idioma/exceptions.py
idioma/gtoken.py
idioma/models.py
idioma/retry_transport.py
idioma/translator.py
idioma/urls.py
idioma/utils.py
idioma-0.0.10.data/scripts/translate
idioma-0.0.10.dist-info/METADATA
idioma-0.0.10.dist-info/WHEEL
idioma-0.0.10.dist-info/top_level.txt
idioma-0.0.10.dist-info/RECORD
